{
  "name": "Le Pain d'Orée",
  "businessType": "Boulangerie / Pâtisserie",
  "shortDesc": "Artisan boulanger-pâtissier au cœur du 19ème arrondissement",
  "description": "Le Pain d'Orée est une boulangerie-pâtisserie artisanale du 19ème arrondissement de Paris. Chaque jour, pains de tradition, viennoiseries dorées et pâtisseries maison sont préparés avec soin pour régaler le quartier.",
  "city": "Paris",
  "zipCode": "75019",
  "country": "FR",
  "primaryColor": "#c41e1e",
  "secondaryColor": "#1c1c1c",
  "accentColor": "#d4a843"
}
